arches_for_science/__init__.py
arches_for_science/apps.py
arches_for_science/hosts.py
arches_for_science/models.py
arches_for_science/settings.py
arches_for_science/signals.py
arches_for_science/tasks.py
arches_for_science/trigger_functions.py
arches_for_science/urls.py
arches_for_science/wsgi.py
arches_for_science/functions/__init__.py
arches_for_science/functions/multicard_resource_descriptor.py
arches_for_science/locale/messages.pot
arches_for_science/management/__init__.py
arches_for_science/management/commands/__init__.py
arches_for_science/management/commands/update_docs.py
arches_for_science/management/commands/update_manifest_urls.py
arches_for_science/media/css/project.css
arches_for_science/media/css/report_templates.css
arches_for_science/media/img/landing/irises.jpg
arches_for_science/media/img/landing/museum_at_night.jpg
arches_for_science/media/js/afs-settings.js
arches_for_science/media/js/bindings/datatable.js
arches_for_science/media/js/bindings/plotly.js
arches_for_science/media/js/bindings/term-search.js
arches_for_science/media/js/bindings/threePCD.js
arches_for_science/media/js/bindings/threePDB.js
arches_for_science/media/js/bindings/uppy-django-storages.js
arches_for_science/media/js/bindings/uppy.js
arches_for_science/media/js/reports/default.js
arches_for_science/media/js/utils/annotation-utils.js
arches_for_science/media/js/utils/iiif-utils.js
arches_for_science/media/js/utils/label-based-graph-utils.js
arches_for_science/media/js/utils/physical-thing.js
arches_for_science/media/js/utils/report.js
arches_for_science/media/js/utils/xy-parser.js
arches_for_science/media/js/viewmodels/afs-instrument.js
arches_for_science/media/js/views/components/annotation-summary.js
arches_for_science/media/js/views/components/file-upload.js
arches_for_science/media/js/views/components/iiif-viewer.js
arches_for_science/media/js/views/components/resource-instance-creator.js
arches_for_science/media/js/views/components/resource-instance-nodevalue.js
arches_for_science-2.1.0b4.dist-info/licenses/LICENSE
arches_for_science-2.1.0b4.dist-info/METADATA
arches_for_science-2.1.0b4.dist-info/WHEEL
arches_for_science-2.1.0b4.dist-info/top_level.txt
arches_for_science-2.1.0b4.dist-info/RECORD
