Metadata-Version: 2.4
Name: arches-for-science
Version: 2.1.0b4
Author: Arches Project
License-Expression: AGPL-3.0-or-later
Classifier: Development Status :: 4 - Beta
Classifier: Programming Language :: Python
Classifier: Programming Language :: Python :: 3
Classifier: Programming Language :: Python :: 3 :: Only
Classifier: Programming Language :: Python :: 3.10
Classifier: Programming Language :: Python :: 3.11
Classifier: Programming Language :: Python :: 3.12
Classifier: Framework :: Django
Classifier: Framework :: Django :: 4.2
Classifier: Intended Audience :: Developers
Classifier: Intended Audience :: Science/Research
Classifier: Intended Audience :: Information Technology
Requires-Python: >=3.10
License-File: LICENSE
Requires-Dist: arches<8,>=7.6.14
Requires-Dist: supervisor==4.2.1
Requires-Dist: django-pgtrigger==4.9.0
Requires-Dist: django-storages==1.13.2
Requires-Dist: boto3==1.25.3
Requires-Dist: arches-templating>=0.1.2
Dynamic: license-file
